[{"name": "benchmarks.time_box_filter_on_partition", "idx": null, "pretty_name": "benchmarks.time_box_filter_on_partition", "last_rev": 1675, "last_value": 0.0273971789999905, "last_err": 0.0014672788506560701, "prev_value": null, "change_rev": null}, {"name": "benchmarks.time_create_large_catalog", "idx": null, "pretty_name": "benchmarks.time_create_large_catalog", "last_rev": 1675, "last_value": 7.021926891000021, "last_err": 0.9654433904206536, "prev_value": null, "change_rev": null}, {"name": "benchmarks.time_create_midsize_catalog", "idx": null, "pretty_name": "benchmarks.time_create_midsize_catalog", "last_rev": 1675, "last_value": 1.108334521000046, "last_err": 0.04986166026123604, "prev_value": 1.0380284900000447, "change_rev": [null, 1544]}, {"name": "benchmarks.time_kdtree_crossmatch", "idx": null, "pretty_name": "benchmarks.time_kdtree_crossmatch", "last_rev": 1675, "last_value": 0.1823456894999822, "last_err": 0.008883748772225001, "prev_value": 0.101265375999958, "change_rev": [null, 1572]}, {"name": "benchmarks.time_lazy_crossmatch_many_columns_all_suffixes", "idx": null, "pretty_name": "benchmarks.time_lazy_crossmatch_many_columns_all_suffixes", "last_rev": 1675, "last_value": 10.466375184000015, "last_err": 1.017650215707538, "prev_value": 8.262757975000028, "change_rev": [null, 1665]}, {"name": "benchmarks.time_lazy_crossmatch_many_columns_overlapping_suffixes", "idx": null, "pretty_name": "benchmarks.time_lazy_crossmatch_many_columns_overlapping_suffixes", "last_rev": 1675, "last_value": 10.486358760999991, "last_err": 1.317318745974125, "prev_value": 8.176794074499995, "change_rev": [null, 1572]}, {"name": "benchmarks.time_open_many_columns_all", "idx": null, "pretty_name": "benchmarks.time_open_many_columns_all", "last_rev": 1675, "last_value": 3.742605073000007, "last_err": 0.3723153473316851, "prev_value": 4.222215035000318, "change_rev": [1481, 1483]}, {"name": "benchmarks.time_open_many_columns_default", "idx": null, "pretty_name": "benchmarks.time_open_many_columns_default", "last_rev": 1675, "last_value": 0.3666540435000343, "last_err": 0.025081775435493815, "prev_value": 0.6212459390000049, "change_rev": [1481, 1483]}, {"name": "benchmarks.time_open_many_columns_list", "idx": null, "pretty_name": "benchmarks.time_open_many_columns_list", "last_rev": 1675, "last_value": 0.16403483850007206, "last_err": 0.009656962665103271, "prev_value": 0.42102165000000014, "change_rev": [1481, 1483]}, {"name": "benchmarks.time_polygon_search", "idx": null, "pretty_name": "benchmarks.time_polygon_search", "last_rev": 1675, "last_value": 0.04625827649999792, "last_err": 0.0021808433385255323, "prev_value": null, "change_rev": null}, {"name": "benchmarks.time_save_big_catalog", "idx": null, "pretty_name": "benchmarks.time_save_big_catalog", "last_rev": 1675, "last_value": 9.8655846085, "last_err": 0.4568697055362784, "prev_value": 20.399519661499994, "change_rev": [null, 1625]}]