[{"name": "benchmarks.time_box_filter_on_partition", "idx": null, "pretty_name": "benchmarks.time_box_filter_on_partition", "last_rev": 1557, "last_value": 0.027053841499991904, "last_err": 0.0012819801437114016, "prev_value": null, "change_rev": null}, {"name": "benchmarks.time_create_large_catalog", "idx": null, "pretty_name": "benchmarks.time_create_large_catalog", "last_rev": 1557, "last_value": 7.321075499000003, "last_err": 0.10393575486926504, "prev_value": 6.898358340499726, "change_rev": [null, 1544]}, {"name": "benchmarks.time_create_midsize_catalog", "idx": null, "pretty_name": "benchmarks.time_create_midsize_catalog", "last_rev": 1557, "last_value": 1.1085875515000225, "last_err": 0.007570924194323506, "prev_value": 1.0380284900000447, "change_rev": [null, 1544]}, {"name": "benchmarks.time_kdtree_crossmatch", "idx": null, "pretty_name": "benchmarks.time_kdtree_crossmatch", "last_rev": 1557, "last_value": 0.10093502649999664, "last_err": 0.003427699679013322, "prev_value": 0.08922571450011674, "change_rev": [null, 1436]}, {"name": "benchmarks.time_lazy_crossmatch_many_columns_all_suffixes", "idx": null, "pretty_name": "benchmarks.time_lazy_crossmatch_many_columns_all_suffixes", "last_rev": 1557, "last_value": 8.135947745500005, "last_err": 0.6559511302491743, "prev_value": 8.604344085999998, "change_rev": [1481, 1483]}, {"name": "benchmarks.time_lazy_crossmatch_many_columns_overlapping_suffixes", "idx": null, "pretty_name": "benchmarks.time_lazy_crossmatch_many_columns_overlapping_suffixes", "last_rev": 1557, "last_value": 8.180888704500006, "last_err": 0.8831022539737805, "prev_value": 8.714135906000138, "change_rev": [1481, 1483]}, {"name": "benchmarks.time_open_many_columns_all", "idx": null, "pretty_name": "benchmarks.time_open_many_columns_all", "last_rev": 1557, "last_value": 3.8079030760000308, "last_err": 0.3189436207359116, "prev_value": null, "change_rev": null}, {"name": "benchmarks.time_open_many_columns_default", "idx": null, "pretty_name": "benchmarks.time_open_many_columns_default", "last_rev": 1557, "last_value": 0.36587842949998617, "last_err": 0.018787968419121493, "prev_value": 0.6212459390000049, "change_rev": [1481, 1483]}, {"name": "benchmarks.time_open_many_columns_list", "idx": null, "pretty_name": "benchmarks.time_open_many_columns_list", "last_rev": 1557, "last_value": 0.16421512700000562, "last_err": 0.010655795238777127, "prev_value": 0.42102165000000014, "change_rev": [1481, 1483]}, {"name": "benchmarks.time_polygon_search", "idx": null, "pretty_name": "benchmarks.time_polygon_search", "last_rev": 1557, "last_value": 0.045622816499985674, "last_err": 0.001589299896521563, "prev_value": null, "change_rev": null}, {"name": "benchmarks.time_save_big_catalog", "idx": null, "pretty_name": "benchmarks.time_save_big_catalog", "last_rev": 1557, "last_value": 19.571820105499967, "last_err": 0.34313625524404445, "prev_value": 20.22841681350002, "change_rev": [1488, 1490]}]