[{"name": "benchmarks.time_box_filter_on_partition", "idx": null, "pretty_name": "benchmarks.time_box_filter_on_partition", "last_rev": 1236, "last_value": 0.024344640499975867, "last_err": 0.0003269976587183269, "prev_value": 0.012619935999993004, "change_rev": [1149, 1160]}, {"name": "benchmarks.time_create_large_catalog", "idx": null, "pretty_name": "benchmarks.time_create_large_catalog", "last_rev": 1236, "last_value": 6.294609970500005, "last_err": 0.23303110742388905, "prev_value": null, "change_rev": null}, {"name": "benchmarks.time_create_midsize_catalog", "idx": null, "pretty_name": "benchmarks.time_create_midsize_catalog", "last_rev": 1236, "last_value": 0.936783123500021, "last_err": 0.012690575385724736, "prev_value": null, "change_rev": null}, {"name": "benchmarks.time_kdtree_crossmatch", "idx": null, "pretty_name": "benchmarks.time_kdtree_crossmatch", "last_rev": 1236, "last_value": 0.08085270999998784, "last_err": 0.0036542346684531367, "prev_value": null, "change_rev": null}, {"name": "benchmarks.time_polygon_search", "idx": null, "pretty_name": "benchmarks.time_polygon_search", "last_rev": 1236, "last_value": 0.027328051500035144, "last_err": 0.003968624423463322, "prev_value": null, "change_rev": null}]