{"commit_hash": "2225b1ef623fd4d98181f43c78da7d15aafd213c", "env_name": "virtualenv-py3.10-Cython-build-packaging", "date": 1729686736000, "params": {"machine": "gh-runner", "python": "3.10", "Cython": "", "build": "", "packaging": ""}, "python": "3.10", "requirements": {"Cython": "", "build": "", "packaging": ""}, "env_vars": {}, "result_columns": ["result", "params", "version", "started_at", "duration", "stats_ci_99_a", "stats_ci_99_b", "stats_q_25", "stats_q_75", "stats_number", "stats_repeat", "samples", "profile"], "results": {"benchmarks.time_box_filter_on_partition": [null, [], "b082de7cc2e9a8751b38a70266508b8c47746389e8365c18170de2ea3de3278b", 1729686834708, 0.053566], "benchmarks.time_create_large_catalog": [null, [], "b7269a6892c684b6e767fe124c092484acfde95f07eb85d305b5baa0f492690e", 1729686834761, 0.016861], "benchmarks.time_create_midsize_catalog": [null, [], "1bb7ec29f4f7be3c1ddb7cb5b3d00ed0220d01824d6e98f372d180527d468acd", 1729686834778, 0.016274], "benchmarks.time_kdtree_crossmatch": [[0.10788717500003031], [], "331530da4eac25967595fcb3d58955d2f5f4c35ba05b97c36a13f66d0cb0c800", 1729686836062, 1.726, [0.1055], [0.10944], [0.10596], [0.10893], [1], [10]], "benchmarks.time_polygon_search": [[0.033335910499999954], [], "bdebab02cc8d570e0f4492ba5939fbcabeb3eefaed8b9908cbf557cc6412b432", 1729686836875, 0.71364, [0.032604], [0.035064], [0.033023], [0.033694], [1], [10]]}, "durations": {}, "version": 2}