{"commit_hash": "49e53b523c9da5231abf6f03c0782a31628f1cf5", "env_name": "virtualenv-py3.10-Cython-build-packaging", "date": 1709930817000, "params": {"machine": "gh-runner", "python": "3.10", "Cython": "", "build": "", "packaging": ""}, "python": "3.10", "requirements": {"Cython": "", "build": "", "packaging": ""}, "env_vars": {}, "result_columns": ["result", "params", "version", "started_at", "duration", "stats_ci_99_a", "stats_ci_99_b", "stats_q_25", "stats_q_75", "stats_number", "stats_repeat", "samples", "profile"], "results": {"benchmarks.time_box_filter_on_partition": [[0.0056953749999877346], [], "5d69dfcb0f3773acd43c4c38ee79e487d83f96f0ab4b8d6e544f10a40daa94a8", 1709930906547, 0.44817, [0.0052955], [0.0067724], [0.0055618], [0.0058872], [1], [10]], "benchmarks.time_kdtree_crossmatch": [[0.03715071649997981], [], "331530da4eac25967595fcb3d58955d2f5f4c35ba05b97c36a13f66d0cb0c800", 1709930906740, 0.78405, [0.036603], [0.038214], [0.036774], [0.03753], [1], [10]], "benchmarks.time_polygon_search": [null, [], "bdebab02cc8d570e0f4492ba5939fbcabeb3eefaed8b9908cbf557cc6412b432", 1715196443333, 0.02039], "benchmarks.time_create_large_catalog": [[4.1044164344998535], [], "7e8b42473c80fc7d59c8e4722d3ab10b5d12c28796038e26179a39bc9c7cbe06", 1714060902212, 25.229, [3.8066], [4.4034], [4.0059], [4.2036], [1], [4]], "benchmarks.time_create_midsize_catalog": [[0.636518884499992], [], "b7c05eccad45a3cac84aba33651625f6b264577b74e5b8aa2a096433ca598d6d", 1714060914826, 7.7551, [0.60645], [0.64167], [0.63264], [0.63807], [1], [10]]}, "durations": {"<build>": 8.860445261001587}, "version": 2}