{"commit_hash": "4fef4284e0b8640fe451c1a20387b1a159814dec", "env_name": "virtualenv-py3.10-Cython-build-packaging", "date": 1730226639000, "params": {"machine": "gh-runner", "python": "3.10", "Cython": "", "build": "", "packaging": ""}, "python": "3.10", "requirements": {"Cython": "", "build": "", "packaging": ""}, "env_vars": {}, "result_columns": ["result", "params", "version", "started_at", "duration", "stats_ci_99_a", "stats_ci_99_b", "stats_q_25", "stats_q_75", "stats_number", "stats_repeat", "samples", "profile"], "results": {"benchmarks.time_box_filter_on_partition": [[0.018505110000006653], [], "99b13d7c6b1da29c3a0930c8edc692a7271ca475af3999272d6b9acdb8dca952", 1730226759526, 0.43959, [0.017914], [0.018931], [0.018195], [0.018611], [1], [10]], "benchmarks.time_create_large_catalog": [[14.862346061999972], [], "b7269a6892c684b6e767fe124c092484acfde95f07eb85d305b5baa0f492690e", 1730226759748, 59.409, [13.304], [16.421], [14.847], [14.878], [1], [2]], "benchmarks.time_create_midsize_catalog": [[2.206545601500011], [], "1bb7ec29f4f7be3c1ddb7cb5b3d00ed0220d01824d6e98f372d180527d468acd", 1730226789534, 22.173, [2.1603], [2.2777], [2.1946], [2.222], [1], [8]], "benchmarks.time_kdtree_crossmatch": [[0.10950391500000478], [], "331530da4eac25967595fcb3d58955d2f5f4c35ba05b97c36a13f66d0cb0c800", 1730226800705, 4.1469, [0.107], [0.11483], [0.10827], [0.11179], [1], [10]], "benchmarks.time_polygon_search": [[0.034400575500001196], [], "bdebab02cc8d570e0f4492ba5939fbcabeb3eefaed8b9908cbf557cc6412b432", 1730226802787, 0.73675, [0.033827], [0.03497], [0.034016], [0.034484], [1], [10]]}, "durations": {}, "version": 2}