{"commit_hash": "c06454cda8a104debadf01f0bbd6538a358831dc", "env_name": "virtualenv-py3.10-Cython-build-packaging", "date": 1715175923000, "params": {"machine": "gh-runner", "python": "3.10", "Cython": "", "build": "", "packaging": ""}, "python": "3.10", "requirements": {"Cython": "", "build": "", "packaging": ""}, "env_vars": {}, "result_columns": ["result", "params", "version", "started_at", "duration", "stats_ci_99_a", "stats_ci_99_b", "stats_q_25", "stats_q_75", "stats_number", "stats_repeat", "samples", "profile"], "results": {"benchmarks.time_box_filter_on_partition": [[0.005928211500005887], [], "5d69dfcb0f3773acd43c4c38ee79e487d83f96f0ab4b8d6e544f10a40daa94a8", 1715176039411, 0.44, [0.0053375], [0.0067311], [0.0056776], [0.0061151], [1], [10]], "benchmarks.time_create_large_catalog": [[3.2295013190000077], [], "7e8b42473c80fc7d59c8e4722d3ab10b5d12c28796038e26179a39bc9c7cbe06", 1715176039634, 25.932, [3.218], [3.2379], [3.2288], [3.2339], [1], [6]], "benchmarks.time_create_midsize_catalog": [[0.49546967099999506], [], "b7c05eccad45a3cac84aba33651625f6b264577b74e5b8aa2a096433ca598d6d", 1715176052598, 6.0642, [0.48713], [0.53668], [0.49214], [0.49997], [1], [10]], "benchmarks.time_kdtree_crossmatch": [[0.03467841849999331], [], "331530da4eac25967595fcb3d58955d2f5f4c35ba05b97c36a13f66d0cb0c800", 1715176055613, 0.78866, [0.034063], [0.035861], [0.034435], [0.035288], [1], [10]], "benchmarks.time_polygon_search": [[0.01243347349999624], [], "e6a330ca87dc744c12b49ade55f880ef0921ae8de5cdfffcb174d51e38b37943", 1715176056012, 0.51592, [0.01121], [0.013748], [0.011598], [0.01272], [1], [10]]}, "durations": {}, "version": 2}