{"commit_hash": "ed5bfe9bcac295c5bfe518f1fb65d819a3a0a3aa", "env_name": "virtualenv-py3.10-Cython-build-packaging", "date": 1700172017000, "params": {"machine": "gh-runner", "python": "3.10", "Cython": "", "build": "", "packaging": ""}, "python": "3.10", "requirements": {"Cython": "", "build": "", "packaging": ""}, "env_vars": {}, "result_columns": ["result", "params", "version", "started_at", "duration", "stats_ci_99_a", "stats_ci_99_b", "stats_q_25", "stats_q_75", "stats_number", "stats_repeat", "samples", "profile"], "results": {"benchmarks.time_kdtree_crossmatch": [null, [], "331530da4eac25967595fcb3d58955d2f5f4c35ba05b97c36a13f66d0cb0c800", 1709323499225, 0.014836], "benchmarks.time_polygon_search": [null, [], "bdebab02cc8d570e0f4492ba5939fbcabeb3eefaed8b9908cbf557cc6412b432", 1715197538444, 0.01674], "benchmarks.time_box_filter_on_partition": [null, [], "b082de7cc2e9a8751b38a70266508b8c47746389e8365c18170de2ea3de3278b", 1715805420021, 0.014961], "benchmarks.time_create_large_catalog": [null, [], "7e8b42473c80fc7d59c8e4722d3ab10b5d12c28796038e26179a39bc9c7cbe06", 1714062352700, 0.016679], "benchmarks.time_create_midsize_catalog": [null, [], "b7c05eccad45a3cac84aba33651625f6b264577b74e5b8aa2a096433ca598d6d", 1714062352717, 0.013193]}, "durations": {"<build>": 8.803700923919678}, "version": 2}